formkit_ninja/__init__.py
formkit_ninja/__main__.py
formkit_ninja/admin.py
formkit_ninja/api.py
formkit_ninja/fields.py
formkit_ninja/formkit_schema.py
formkit_ninja/management/__init__.py
formkit_ninja/management/commands/__init__.py
formkit_ninja/management/commands/import_forms.py
formkit_ninja/migrations/0001_initial.py
formkit_ninja/migrations/0002_alter_formcomponents_label_alter_formkitschema_key.py
formkit_ninja/migrations/0003_delete_translatable.py
formkit_ninja/migrations/0004_remove_formkitschema_key_and_more.py
formkit_ninja/migrations/0005_option_last_updated_option_object_id_optionlabel_and_more.py
formkit_ninja/migrations/0006_option_group_option_unique_option_id.py
formkit_ninja/migrations/0007_alter_option_field.py
formkit_ninja/migrations/0008_remove_option_label.py
formkit_ninja/migrations/0009_formkitschemanode_text_content_and_more.py
formkit_ninja/migrations/0010_alter_option_options_and_more.py
formkit_ninja/migrations/0011_nodechildren_formkitschemanode_children.py
formkit_ninja/migrations/0012_remove_formkitschemanode_group_remove_option_field_and_more.py
formkit_ninja/migrations/0013_formkitschemanode_option_group.py
formkit_ninja/migrations/0014_schemalabel_schemadescription.py
formkit_ninja/migrations/0015_alter_formkitschema_label.py
formkit_ninja/migrations/0016_alter_nodechildren_options_and_more.py
formkit_ninja/migrations/0017_nodechildren_change_id.py
formkit_ninja/migrations/0018_remove_formcomponents_order_on_insert_option_and_more.py
formkit_ninja/migrations/0019_formkitschemanode_track_change_and_more.py
formkit_ninja/migrations/0020_remove_formcomponents_order_on_update_option_and_more.py
formkit_ninja/migrations/0021_formkitschemanode_is_active.py
formkit_ninja/migrations/0022_formkitschemanode_soft_delete.py
formkit_ninja/migrations/__init__.py
formkit_ninja/models.py
formkit_ninja/parser/__init__.py
formkit_ninja/parser/logger.py
formkit_ninja/parser/templates/admin.jinja2
formkit_ninja/parser/templates/admin.py.jinja2
formkit_ninja-0.8.0.dist-info/METADATA
formkit_ninja-0.8.0.dist-info/WHEEL
formkit_ninja-0.8.0.dist-info/RECORD
