Metadata-Version: 2.1
Name: formkit-ninja
Version: 0.8.0
Summary: A Django-Ninja backend to specify FormKit schemas
Home-page: https://github.com/catalpainternational/formkit-ninja
License: GPLv3
Author: Josh Brooks
Author-email: josh@catalpa.io
Requires-Python: >=3.10,<4.0
Classifier: License :: Other/Proprietary License
Classifier: Programming Language :: Python :: 3
Classifier: Programming Language :: Python :: 3.10
Classifier: Programming Language :: Python :: 3.11
Requires-Dist: Django (>=4,<5)
Requires-Dist: django-ninja (>=0.21,<0.22)
Requires-Dist: django-pgtrigger (>=4.7.0,<5.0.0)
Requires-Dist: django-stubs[compatible-mypy] (>=4.2.3,<5.0.0)
Requires-Dist: pydantic (<2)
Requires-Dist: rich
Project-URL: Repository, https://github.com/catalpainternational/formkit-ninja
